MatrixBabou/NMFALS.py
MatrixBabou/__init__.py
MatrixBabou/krylov.py
MatrixBabou/mat_prod.py
MatrixBabou/quantum.py
MatrixBabou-0.1.6.dist-info/LICENSE
MatrixBabou-0.1.6.dist-info/METADATA
MatrixBabou-0.1.6.dist-info/WHEEL
MatrixBabou-0.1.6.dist-info/top_level.txt
MatrixBabou-0.1.6.dist-info/RECORD
