Metadata-Version: 2.1
Name: MatrixBabou
Version: 0.1.6
Summary: This library is for linear algebra, Matrix analysis 
Home-page: https://github.com/mohamedlaminebabou/BABOUMATH/
Author: Babou Mohamed Lamine 
Author-email: mohamedlaminebabou@gmail.com
License: MIT
Keywords: python,matrix,Matrix product,Matrix analysis
Platform: UNKNOWN
Classifier: Development Status :: 1 - Planning
Classifier: Intended Audience :: Developers
Classifier: Programming Language :: Python :: 3
Classifier: Operating System :: Unix
Classifier: Operating System :: MacOS :: MacOS X
Classifier: Operating System :: Microsoft :: Windows
License-File: LICENSE
Requires-Dist: numba
Requires-Dist: numpy
Requires-Dist: pyccel
Requires-Dist: cython
Requires-Dist: qiskit
